rda_python_globus/__init__.py
rda_python_globus/file_management.py
rda_python_globus/list.py
rda_python_globus/main.py
rda_python_globus/task_management.py
rda_python_globus/transfer.py
rda_python_globus/lib/__init__.py
rda_python_globus/lib/auth.py
rda_python_globus/lib/config.py
rda_python_globus-1.0.5.dist-info/licenses/LICENSE
rda_python_globus-1.0.5.dist-info/METADATA
rda_python_globus-1.0.5.dist-info/WHEEL
rda_python_globus-1.0.5.dist-info/entry_points.txt
rda_python_globus-1.0.5.dist-info/top_level.txt
rda_python_globus-1.0.5.dist-info/RECORD
