Metadata-Version: 2.4
Name: rda_python_globus
Version: 1.0.5
Summary: Tools for managing Globus transfers supporting the NSF NCAR Geoscience Data Exchange (GDEX) project.
Author-email: Thomas Cram <tcram@ucar.edu>
Project-URL: Homepage, https://github.com/NCAR/rda-python-globus
Classifier: Programming Language :: Python :: 3
Classifier: License :: OSI Approved :: MIT License
Classifier: Operating System :: OS Independent
Classifier: Development Status :: 5 - Production/Stable
Requires-Python: >=3.11
License-File: LICENSE
Requires-Dist: globus_sdk<4.0.0
Requires-Dist: click>=8.3.0
Requires-Dist: pyyaml
Requires-Dist: six
Dynamic: license-file
